.gitignore
LICENSE
README.md
setup.cfg
setup.py
piproc/__init__.py
piproc/main.py
piproc/tables.py
piproc.egg-info/PKG-INFO
piproc.egg-info/SOURCES.txt
piproc.egg-info/dependency_links.txt
piproc.egg-info/requires.txt
piproc.egg-info/top_level.txt