Metadata-Version: 2.1
Name: piproc
Version: 0.2.3
Summary: A package which connects Plastic-i projects with a processing database
Home-page: https://gitlab.com/plastic-i/piproc
Author: Plastic-i
Keywords: piproc
Requires-Python: >=3.9
License-File: LICENSE
Requires-Dist: geoalchemy2
Requires-Dist: sqlalchemy
Requires-Dist: shapely
Requires-Dist: boto3
Requires-Dist: psycopg2
Requires-Dist: pyyaml
